Metadata-Version: 2.1
Name: cow-saying
Version: 0.0.1
Summary: My Package
Author: Cow From USA
Author-email: askerovsul18@gmail.com
